[{"place_id": 47480579, "licence": "Data \u00a9 OpenStreetMap contributors, ODbL 1.0. https://osm.org/copyright", "osm_type": "node", "osm_id": 4149129195, "boundingbox": ["51.1848672", "51.1849672", "21.2687285", "21.2688285"], "lat": "51.1849172", "lon": "21.2687785", "display_name": "1, W\u00f3jtowski M\u0142yn, W\u00f3jtostwo, I\u0142\u017ca, gmina I\u0142\u017ca, Radom County, Masovian Voivodeship, 27-100, Poland", "class": "place", "type": "house", "importance": 0.4200099999999999, "geojson": {"type": "Point", "coordinates": [21.2687785, 51.1849172]}}]